hotimport_core/__init__.py
hotimport_core/watcher.py
xontrib/hotimport.py
xontrib_hotimport-0.0.1a0.dist-info/METADATA
xontrib_hotimport-0.0.1a0.dist-info/WHEEL
xontrib_hotimport-0.0.1a0.dist-info/RECORD
