Metadata-Version: 2.1
Name: xontrib-hotimport
Version: 0.0.1a0
Summary: 
Author: Your Name
Author-email: you@example.com
Requires-Python: >=3.12,<4.0
Classifier: Programming Language :: Python :: 3
Classifier: Programming Language :: Python :: 3.12
Classifier: Programming Language :: Python :: 3.13
Requires-Dist: rich (>=13.9.4,<14.0.0)
Requires-Dist: watchfiles (>=0.24.0,<0.25.0)
Requires-Dist: xonsh (>=0.18.4,<0.19.0)
